quantifyindia/__init__.py
quantifyindia/historical_data.py
quantifyindia/nse_data.py
tests/__init__.py
tests/test_quantifyindia.py
quantifyindia-0.5.dist-info/METADATA
quantifyindia-0.5.dist-info/WHEEL
quantifyindia-0.5.dist-info/top_level.txt
quantifyindia-0.5.dist-info/RECORD
