Metadata-Version: 2.1
Name: quantifyindia
Version: 0.5
Summary: A package for fetching real-time and historical stock data from NSE and Alpha Vantage
Home-page: https://github.com/Parthchauh/quantifyindia
Author: Parth Chauhan
Author-email: cparth495@gmail.com
Requires-Dist: nsetools
Requires-Dist: requests
